pyprocessors_pseudonimizer/__init__.py
pyprocessors_pseudonimizer/fakerop.py
pyprocessors_pseudonimizer/pseudonimizer.py
pyprocessors_pseudonimizer-0.5.92.dist-info/entry_points.txt
pyprocessors_pseudonimizer-0.5.92.dist-info/WHEEL
pyprocessors_pseudonimizer-0.5.92.dist-info/METADATA
pyprocessors_pseudonimizer-0.5.92.dist-info/RECORD
